{
  "$schema": "https://developer.microsoft.com/json-schemas/fabric/item/report/definition/visualContainer/2.5.0/schema.json",
  "name": "de4cce0f2bc2c5ffadea",
  "position": {
    "x": 19.9322951929587,
    "y": 19.9322951929587,
    "z": 1002,
    "height": 51.997291807718355,
    "width": 620.50101557210564
  },
  "visual": {
    "visualType": "textbox",
    "objects": {
      "general": [
        {
          "properties": {
            "paragraphs": [
              {
                "textRuns": [
                  {
                    "value": "Solar Production",
                    "textStyle": {
                      "fontWeight": "bold",
                      "fontFamily": "Segoe UI",
                      "fontSize": "18pt"
                    }
                  }
                ]
              }
            ]
          }
        }
      ]
    },
    "drillFilterOtherVisuals": true
  },
  "howCreated": "Copilot"
}